{
  "tinder": {
    "hash": "272c00ac2fea4ba5",
    "count": 2,
    "flip_count": 0,
    "fetch_failure_streak": 0,
    "fetch_blocked": false,
    "run_confirmations": 2,
    "semantic_run_confirmations": 2,
    "semantic_signature": "restriction:no_refund_or_final_sale",
    "change_key": "restriction:no_refund_or_final_sale",
    "signal_window_hash_decision": "restriction:no_refund_or_final_sale",
    "signal_window_change_decision": "restriction:no_refund_or_final_sale",
    "signal_window_required_votes": 2,
    "signal_window_top_hash_votes": 2,
    "signal_window_baseline_votes": 3,
    "actual_confirm_runs_required": 3,
    "metadata_confirm_runs_required": 3,
    "metadata_signature": "0bc063ab89b545dc",
    "previous_metadata_signature": "e18c5ea37454df39",
    "metadata_signal_stable": false,
    "last_run_observed_utc": "2026-05-27T09:07:53Z",
    "source_url": "https://www.help.tinder.com/hc/en-us/articles/115003521343-Refund-Requests",
    "pending_since_utc": "2026-05-27T09:07:53Z",
    "first_seen_utc": "2026-05-27T09:07:53Z",
    "last_seen_utc": "2026-05-27T09:10:17Z",
    "baseline_observations": 0,
    "profile": {
      "hash": "272c00ac2fea4ba5",
      "source_url": "https://www.help.tinder.com/hc/en-us/articles/115003521343-Refund-Requests",
      "extracted_at_utc": "2026-05-27T09:09:55Z",
      "tokens": [
        "restriction:no_refund_or_final_sale"
      ],
      "page_metadata": {
        "source_kind": "zendesk_article_json",
        "source_title": "Refund Requests",
        "display_last_updated_label": "",
        "display_last_updated_date_utc": "",
        "display_effective_date_label": "",
        "display_effective_date_utc": "",
        "source_updated_at_utc": "2025-12-16T15:47:26Z",
        "source_edited_at_utc": "2025-04-14T09:17:12Z"
      },
      "metadata_signature": "0bc063ab89b545dc"
    },
    "quality_gate_passes": 3,
    "quality_gate_failures": 0,
    "quality_gate_last_reason": "",
    "quality_gate_last_observed_utc": "2026-05-27T09:10:17Z",
    "quality_gate_policy_hits": 5,
    "quality_gate_lines": 12,
    "quality_gate_chars": 1519,
    "volatility_tier": "flaky",
    "pending_model_id": "signal-v2",
    "pending_model_first_observed_utc": "2026-05-27T09:07:53Z"
  },
  "mlb_tv": {
    "hash": "eefa7c510adbc72c",
    "count": 1,
    "flip_count": 5,
    "fetch_failure_streak": 0,
    "fetch_blocked": false,
    "run_confirmations": 1,
    "semantic_run_confirmations": 1,
    "semantic_signature": "",
    "change_key": "eefa7c510adbc72c",
    "signal_window_hash_decision": "",
    "signal_window_change_decision": "",
    "signal_window_required_votes": 3,
    "signal_window_top_hash_votes": 1,
    "signal_window_baseline_votes": 2,
    "actual_confirm_runs_required": 2,
    "metadata_confirm_runs_required": 2,
    "metadata_signature": "ea7c709252c84b20",
    "previous_metadata_signature": "ca408a9a4f39c726",
    "metadata_signal_stable": false,
    "last_run_observed_utc": "2026-05-27T09:08:47Z",
    "source_url": "https://www.mlb.com/live-stream-games/help-center",
    "pending_since_utc": "2026-05-27T02:17:00Z",
    "first_seen_utc": "2026-05-27T09:10:13Z",
    "last_seen_utc": "2026-05-27T09:10:13Z",
    "baseline_observations": 0,
    "profile": {
      "hash": "eefa7c510adbc72c",
      "source_url": "https://www.mlb.com/live-stream-games/help-center",
      "extracted_at_utc": "2026-05-27T09:10:13Z",
      "tokens": [],
      "page_metadata": {
        "source_kind": "html",
        "source_title": "",
        "display_last_updated_label": "",
        "display_last_updated_date_utc": "",
        "display_effective_date_label": "",
        "display_effective_date_utc": "",
        "source_updated_at_utc": "",
        "source_edited_at_utc": ""
      },
      "metadata_signature": "ea7c709252c84b20"
    },
    "quality_gate_passes": 3,
    "quality_gate_failures": 0,
    "quality_gate_last_reason": "",
    "quality_gate_last_observed_utc": "2026-05-27T09:10:13Z",
    "quality_gate_policy_hits": 1,
    "quality_gate_lines": 10,
    "quality_gate_chars": 361,
    "volatility_tier": "normal",
    "pending_model_id": "signal-v2",
    "pending_model_first_observed_utc": "2026-05-27T09:08:47Z"
  }
}
