{
  "audible": {
    "hash": "66f213551c17b902",
    "count": 1,
    "flip_count": 23,
    "run_confirmations": 1,
    "actual_confirm_runs_required": 2,
    "last_run_observed_utc": "2026-03-01T01:22:30Z",
    "source_url": "https://help.audible.com/s/article/how-do-i-cancel-my-audible-membership",
    "pending_since_utc": "2026-02-27T06:45:24Z",
    "first_seen_utc": "2026-03-01T01:26:27Z",
    "last_seen_utc": "2026-03-01T01:26:27Z",
    "baseline_observations": 0,
    "profile": {
      "hash": "66f213551c17b902",
      "source_url": "https://help.audible.com/s/article/how-do-i-cancel-my-audible-membership",
      "extracted_at_utc": "2026-03-01T01:26:27Z",
      "tokens": []
    }
  },
  "canva": {
    "hash": "c685ab6f3f347585",
    "count": 1,
    "flip_count": 168,
    "run_confirmations": 1,
    "actual_confirm_runs_required": 3,
    "last_run_observed_utc": "2026-03-01T01:22:37Z",
    "source_url": "https://www.canva.com/help/cancellation/",
    "pending_since_utc": "2026-02-18T08:56:18Z",
    "first_seen_utc": "2026-03-01T01:26:21Z",
    "last_seen_utc": "2026-03-01T01:26:21Z",
    "baseline_observations": 0,
    "profile": {
      "hash": "c685ab6f3f347585",
      "source_url": "https://www.canva.com/help/cancellation/",
      "extracted_at_utc": "2026-03-01T01:26:21Z",
      "tokens": []
    }
  },
  "espn_plus": {
    "hash": "c2486b589cb4792b",
    "count": 2,
    "flip_count": 21,
    "run_confirmations": 1,
    "actual_confirm_runs_required": 2,
    "last_run_observed_utc": "2026-03-01T01:22:44Z",
    "source_url": "https://www.espn.com/espnplus/",
    "pending_since_utc": "2026-02-25T00:26:50Z",
    "first_seen_utc": "2026-03-01T01:25:59Z",
    "last_seen_utc": "2026-03-01T01:26:19Z",
    "baseline_observations": 0,
    "profile": {
      "hash": "c2486b589cb4792b",
      "source_url": "https://www.espn.com/espnplus/",
      "extracted_at_utc": "2026-03-01T01:26:19Z",
      "tokens": []
    }
  },
  "midjourney": {
    "hash": "cda38716917340a8",
    "count": 2,
    "flip_count": 10,
    "run_confirmations": 1,
    "actual_confirm_runs_required": 2,
    "last_run_observed_utc": "2026-03-01T01:23:59Z",
    "source_url": "https://docs.midjourney.com/hc/en-us/articles/25383543872269-Manage-Your-Subscription-Plan",
    "pending_since_utc": "2026-02-28T01:07:33Z",
    "first_seen_utc": "2026-03-01T01:26:11Z",
    "last_seen_utc": "2026-03-01T01:26:29Z",
    "baseline_observations": 0,
    "profile": {
      "hash": "cda38716917340a8",
      "source_url": "https://docs.midjourney.com/hc/en-us/articles/25383543872269-Manage-Your-Subscription-Plan",
      "extracted_at_utc": "2026-03-01T01:26:29Z",
      "tokens": []
    }
  },
  "paramount_plus": {
    "hash": "6a7e4d8860b1d9ac",
    "count": 1,
    "flip_count": 165,
    "run_confirmations": 1,
    "actual_confirm_runs_required": 3,
    "last_run_observed_utc": "2026-03-01T01:24:09Z",
    "source_url": "https://help.paramountplus.com/s/article/PD-How-do-I-cancel-my-Paramount-subscription",
    "pending_since_utc": "2026-02-18T08:57:50Z",
    "first_seen_utc": "2026-03-01T01:26:36Z",
    "last_seen_utc": "2026-03-01T01:26:36Z",
    "baseline_observations": 0,
    "profile": {
      "hash": "6a7e4d8860b1d9ac",
      "source_url": "https://help.paramountplus.com/s/article/PD-How-do-I-cancel-my-Paramount-subscription",
      "extracted_at_utc": "2026-03-01T01:26:36Z",
      "tokens": []
    }
  },
  "twitch": {
    "hash": "c51436531a9cfd64",
    "count": 1,
    "flip_count": 170,
    "run_confirmations": 1,
    "actual_confirm_runs_required": 3,
    "last_run_observed_utc": "2026-03-01T01:24:33Z",
    "source_url": "https://help.twitch.tv/s/article/cancel-twitch-turbo",
    "pending_since_utc": "2026-02-18T08:57:57Z",
    "first_seen_utc": "2026-03-01T01:26:35Z",
    "last_seen_utc": "2026-03-01T01:26:35Z",
    "baseline_observations": 0,
    "profile": {
      "hash": "c51436531a9cfd64",
      "source_url": "https://help.twitch.tv/s/article/cancel-twitch-turbo",
      "extracted_at_utc": "2026-03-01T01:26:35Z",
      "tokens": []
    }
  },
  "fitbit_premium": {
    "hash": "4084dde0e6b8dde4",
    "count": 1,
    "flip_count": 174,
    "run_confirmations": 1,
    "actual_confirm_runs_required": 3,
    "last_run_observed_utc": "2026-03-01T01:24:41Z",
    "source_url": "https://support.google.com/fitbit/",
    "pending_since_utc": "2026-02-18T08:57:50Z",
    "first_seen_utc": "2026-03-01T01:26:37Z",
    "last_seen_utc": "2026-03-01T01:26:37Z",
    "baseline_observations": 0,
    "profile": {
      "hash": "4084dde0e6b8dde4",
      "source_url": "https://support.google.com/fitbit/",
      "extracted_at_utc": "2026-03-01T01:26:37Z",
      "tokens": []
    }
  }
}
