{
  "myfitnesspal_premium": {
    "hash": "bb3cd928657fe7fc",
    "count": 1,
    "flip_count": 59,
    "source_url": "https://www.myfitnesspal.com/terms-of-use",
    "pending_since_utc": "2026-02-18T08:51:39Z",
    "first_seen_utc": "2026-02-20T18:37:20Z",
    "last_seen_utc": "2026-02-20T18:37:20Z",
    "baseline_observations": 0,
    "profile": {
      "hash": "bb3cd928657fe7fc",
      "source_url": "https://www.myfitnesspal.com/terms-of-use",
      "extracted_at_utc": "2026-02-20T18:37:20Z",
      "tokens": [
        "flow:support_request"
      ]
    }
  }
}
